job_house.py
job_alert-0.1.1.dist-info/entry_points.txt
job_alert-0.1.1.dist-info/WHEEL
job_alert-0.1.1.dist-info/METADATA
job_alert-0.1.1.dist-info/RECORD
