Metadata-Version: 2.1
Name: job-alert
Version: 0.1.1
Summary: job alert is an application that employers logs in and post job offers and job seekers logs in to see jobs posted
Author: Andrew Gabriel
Requires-Python: >3.0
Classifier: Programming Language :: Python :: 3
Classifier: Programming Language :: Python :: 3.4
Classifier: Programming Language :: Python :: 3.5
Classifier: Programming Language :: Python :: 3.6
Classifier: Programming Language :: Python :: 3.7
Classifier: Programming Language :: Python :: 3.8
